crox/__init__.py
crox/__main__.py
crox/core.py
crox-0.1.2.data/scripts/crox
crox-0.1.2.dist-info/DESCRIPTION.rst
crox-0.1.2.dist-info/METADATA
crox-0.1.2.dist-info/RECORD
crox-0.1.2.dist-info/WHEEL
crox-0.1.2.dist-info/metadata.json
crox-0.1.2.dist-info/top_level.txt
