Metadata-Version: 2.0
Name: crox
Version: 0.1.2
Summary: Light-weight general-purpose macro expander
Home-page: https://github.com/gustavla/crox
Author: Gustav Larsson
Author-email: gustav.m.larsson@gmail.com
License: BSD
Platform: UNKNOWN
Classifier: Development Status :: 4 - Beta
Classifier: License :: OSI Approved :: BSD License
Classifier: Programming Language :: Python
Classifier: Programming Language :: Python :: 2
Classifier: Programming Language :: Python :: 2.7
Classifier: Programming Language :: Python :: 3
Classifier: Programming Language :: Python :: 3.4
